gceimgutils/VERSION
gceimgutils/__init__.py
gceimgutils/gcecreateimg.py
gceimgutils/gcedeprecateimg.py
gceimgutils/gcegetblob.py
gceimgutils/gceimgutils.py
gceimgutils/gceimgutilsExceptions.py
gceimgutils/gcelistimg.py
gceimgutils/gceremoveblob.py
gceimgutils/gceremoveimg.py
gceimgutils/gceuploadblob.py
gceimgutils/gceutils.py
gceimgutils-1.4.1.data/scripts/gcecreateimg
gceimgutils-1.4.1.data/scripts/gcedeprecateimg
gceimgutils-1.4.1.data/scripts/gcegetblob
gceimgutils-1.4.1.data/scripts/gcelistimg
gceimgutils-1.4.1.data/scripts/gceremoveblob
gceimgutils-1.4.1.data/scripts/gceremoveimg
gceimgutils-1.4.1.data/scripts/gceuploadblob
gceimgutils-1.4.1.dist-info/licenses/LICENSE
gceimgutils-1.4.1.dist-info/METADATA
gceimgutils-1.4.1.dist-info/WHEEL
gceimgutils-1.4.1.dist-info/top_level.txt
gceimgutils-1.4.1.dist-info/RECORD
