Metadata-Version: 2.4
Name: gceimgutils
Version: 1.4.1
Summary: Command-line tools to manage images in GCE
Home-page: https://github.com/SUSE-Enceladus/gceimgutils
Author: SUSE Public Cloud Team
Author-email: public-cloud-dev@susecloud.net
License: GPLv3+
Classifier: Development Status :: 4 - Beta
Classifier: Intended Audience :: Developers
Classifier: Natural Language :: English
Classifier: License :: OSI Approved :: GNU General Public License v3 or later (GPLv3+)
Classifier: Programming Language :: Python
Classifier: Programming Language :: Python :: 3
Classifier: Programming Language :: Python :: 3.7
Classifier: Programming Language :: Python :: 3.8
Classifier: Programming Language :: Python :: 3.9
Classifier: Programming Language :: Python :: 3.10
Classifier: Programming Language :: Python :: 3.11
Classifier: Programming Language :: Python :: 3.12
Classifier: Programming Language :: Python :: Implementation :: CPython
Classifier: Programming Language :: Python :: Implementation :: PyPy
License-File: LICENSE
Requires-Dist: google-auth
Requires-Dist: google-cloud-compute
Requires-Dist: google-cloud-core
Requires-Dist: google-cloud-storage
Requires-Dist: python-dateutil
Provides-Extra: dev
Requires-Dist: flake8; extra == "dev"
Requires-Dist: mock; extra == "dev"
Requires-Dist: pytest; extra == "dev"
Requires-Dist: pytest-cov; extra == "dev"
Requires-Dist: bumpversion; extra == "dev"
Dynamic: author
Dynamic: author-email
Dynamic: classifier
Dynamic: description
Dynamic: description-content-type
Dynamic: home-page
Dynamic: license
Dynamic: license-file
Dynamic: provides-extra
Dynamic: requires-dist
Dynamic: summary
